ignorem/__init__.py
ignorem/commands.py
ignorem/config.py
ignorem/gitignore.py
ignorem/sources.py
ignorem-1.1.3.dist-info/LICENSE
ignorem-1.1.3.dist-info/METADATA
ignorem-1.1.3.dist-info/WHEEL
ignorem-1.1.3.dist-info/entry_points.txt
ignorem-1.1.3.dist-info/top_level.txt
ignorem-1.1.3.dist-info/RECORD
