Metadata-Version: 2.1
Name: ignorem
Version: 1.1.3
Summary: Easily manage .gitignore files.
Home-page: https://github.com/itsmaxymoo/ignorem
Author: Max Loiacono
Author-email: 
License: MIT License
Platform: UNKNOWN
Classifier: Programming Language :: Python :: 3
Classifier: License :: OSI Approved :: MIT License
Classifier: Operating System :: OS Independent
Requires-Python: >=3.6
License-File: LICENSE
Requires-Dist: simplecfg (<2.0.0)
